CHANGES.rst
MANIFEST.in
README.rst
requirements.txt
setup.py
sc_python_templates.egg-info/PKG-INFO
sc_python_templates.egg-info/SOURCES.txt
sc_python_templates.egg-info/dependency_links.txt
sc_python_templates.egg-info/entry_points.txt
sc_python_templates.egg-info/requires.txt
sc_python_templates.egg-info/top_level.txt
sc_templates/__init__.py
sc_templates/main.py
sc_templates/utils.py
sc_templates/configs/__init__.py
sc_templates/configs/default.py
sc_templates/tests/__init__.py
sc_templates/tests/sample_config/default.yml